partiql-0.202107.0.dist-info/METADATA
partiql-0.202107.0.dist-info/WHEEL
partiql/__init__.py
partiql/partiql.cpython-36m-x86_64-linux-gnu.so
partiql-0.202107.0.dist-info/RECORD
