Metadata-Version: 2.1
Name: partiql
Version: 0.202107.0
Summary: A implementation of PartiQL
Keywords: partiql
Home-Page: https://github.com/fuyutarow/partiql-rs
Author: FUKUDA Yutaro <fuyutarow@gmail.com>
Author-Email: FUKUDA Yutaro <fuyutarow@gmail.com>
License: MIT
